dora_cli/__init__.py
dora_cli/dora_cli.abi3.so
dora_rs_cli_robodriver-0.3.14.dist-info/METADATA
dora_rs_cli_robodriver-0.3.14.dist-info/WHEEL
dora_rs_cli_robodriver-0.3.14.dist-info/entry_points.txt
dora_rs_cli_robodriver-0.3.14.dist-info/RECORD
