Metadata-Version: 2.4
Name: dora-rs-cli-robodriver
Version: 0.3.14
Requires-Dist: dora-rs-robodriver>=0.3.13
Requires-Dist: uv
License: MIT
Requires-Python: >=3.8
